.DS_Store
problystatpy/__init__.py
problystatpy/binomialdistr.py
problystatpy/gaussiandistr.py
problystatpy/generaldistr.py
problystatpy-0.8.3.dist-info/METADATA
problystatpy-0.8.3.dist-info/WHEEL
problystatpy-0.8.3.dist-info/top_level.txt
problystatpy-0.8.3.dist-info/RECORD
