Metadata-Version: 2.1
Name: problystatpy
Version: 0.8.3
Summary: Statististical Probability Distributions
Home-page: https://github.com/jungsnn/problystatPyP
Author: Jenny J. Jung
Author-email: jjung@gmail.com
License: UNKNOWN
Platform: UNKNOWN
Classifier: Programming Language :: Python :: 3
Classifier: License :: OSI Approved :: MIT License
Classifier: Operating System :: MacOS
Classifier: Topic :: Software Development :: Libraries :: Python Modules
